ribotricer/__init__.py
ribotricer/bam.py
ribotricer/cli.py
ribotricer/common.py
ribotricer/const.py
ribotricer/count_orfs.py
ribotricer/detect_orfs.py
ribotricer/fasta.py
ribotricer/gtf.py
ribotricer/infer_protocol.py
ribotricer/interval.py
ribotricer/learn_cutoff.py
ribotricer/metagene.py
ribotricer/orf.py
ribotricer/orf_seq.py
ribotricer/plotting.py
ribotricer/prepare_orfs.py
ribotricer/statistics.py
ribotricer/utils.py
ribotricer-1.4.0.dist-info/AUTHORS
ribotricer-1.4.0.dist-info/LICENSE
ribotricer-1.4.0.dist-info/METADATA
ribotricer-1.4.0.dist-info/WHEEL
ribotricer-1.4.0.dist-info/entry_points.txt
ribotricer-1.4.0.dist-info/top_level.txt
ribotricer-1.4.0.dist-info/RECORD
