Metadata-Version: 2.1
Name: ribotricer
Version: 1.4.0
Summary: Python package to detect translating ORFs from Ribo-seq data
Home-page: https://github.com/smithlabcode/ribotricer
Author: Saket Choudhary, Wenzheng Li
Author-email: saketkc@gmail.com
Maintainer: Saket Choudhary
Maintainer-email: saketkc@gmail.com
License: GPLv3
Classifier: Development Status :: 5 - Production/Stable
Classifier: Environment :: Console
Classifier: Intended Audience :: Science/Research
Classifier: License :: OSI Approved :: GNU General Public License v3 (GPLv3)
Classifier: Natural Language :: English
Classifier: Operating System :: POSIX :: Linux
Classifier: Operating System :: MacOS
Classifier: Operating System :: Microsoft :: Windows
Classifier: Programming Language :: Python :: 3.7
Classifier: Programming Language :: Python :: 3.8
Classifier: Programming Language :: Python :: 3.9
Classifier: Programming Language :: Python :: 3.10
Classifier: Programming Language :: Python :: 3.11
Classifier: Topic :: Scientific/Engineering :: Bio-Informatics
Classifier: Topic :: Utilities
Requires-Python: >=3.7
License-File: LICENSE
License-File: AUTHORS
Requires-Dist: click >=8.1.3
Requires-Dist: click-help-colors >=0.9.1
Requires-Dist: matplotlib >=3.5.3
Requires-Dist: numpy >=1.21.1
Requires-Dist: pandas >=1.3
Requires-Dist: pyfaidx >=0.7.1
Requires-Dist: pysam >=0.19.1
Requires-Dist: quicksect >=0.2.2
Requires-Dist: scipy >=1.7.0
Requires-Dist: tqdm >=4.64.1
